{
	"name": "DelimitedText5",
	"properties": {
		"linkedServiceName": {
			"referenceName": "LS_Sam_BlobStorage",
			"type": "LinkedServiceReference"
		},
		"annotations": [],
		"type": "DelimitedText",
		"typeProperties": {
			"location": {
				"type": "AzureBlobStorageLocation",
				"fileName": "Surrogate1.csv",
				"container": "input"
			},
			"columnDelimiter": ",",
			"escapeChar": "\\",
			"firstRowAsHeader": true,
			"quoteChar": "\""
		},
		"schema": [
			{
				"name": "id",
				"type": "String"
			},
			{
				"name": "name",
				"type": "String"
			},
			{
				"name": "gender",
				"type": "String"
			},
			{
				"name": "department",
				"type": "String"
			}
		]
	}
}